README.md
_repromancy.c
setup.py
_repromancy_spam/__init__.py
_repromancy_spam/_impl/__init__.py
_repromancy_spam/_impl/ham.py
repromancy/__init__.py
repromancy.egg-info/PKG-INFO
repromancy.egg-info/SOURCES.txt
repromancy.egg-info/dependency_links.txt
repromancy.egg-info/top_level.txt
test/test_cast.py
test/test_reprect.py
test/test_targeting.py