Metadata-Version: 2.1
Name: repromancy
Version: 0.0.1
Summary: Utilize dark magic to unify reprs.
Home-page: https://github.com/esoma/repromancy
Author: Erik Soma
Author-email: stillusingirc@gmail.com
License: UNKNOWN
Platform: UNKNOWN
Classifier: Development Status :: 4 - Beta
Classifier: Intended Audience :: Developers
Classifier: License :: OSI Approved :: MIT License
Classifier: Operating System :: OS Independent
Classifier: Programming Language :: Python :: 3
Requires-Python: >=3.6
